[
  {
    "id": 1,
    "title": "Banco de Areia Central",
    "description": "Formação de banco de areia extenso que dificulta a passagem de embarcações de médio porte.",
    "type": "Banco de Areia",
    "riskLevel": "Atenção"
  },
  {
    "id": 2,
    "title": "Pedral Perigoso",
    "description": "Área com pedras submersas, risco alto de colisão e avaria no casco.",
    "type": "Pedral",
    "riskLevel": "Alto Risco"
  },
  {
    "id": 3,
    "title": "Tronco Submerso Próximo à Margem",
    "description": "Risco de colisão com tronco flutuante ou semi-submerso.",
    "type": "Obstáculo",
    "riskLevel": "Atenção"
  },
  {
    "id": 4,
    "title": "Área de Forte Correnteza",
    "description": "Correnteza forte que exige atenção redobrada na navegação.",
    "type": "Condição Fluvial",
    "riskLevel": "Atenção"
  },
  {
    "id": 5,
    "title": "Redemoinho Sazonal",
    "description": "Formação de redemoinhos em períodos de cheia, risco para pequenas embarcações.",
    "type": "Condição Fluvial",
    "riskLevel": "Atenção"
  }
]